galigeopy/__init__.py
galigeopy/galigeopy.py
galigeopy/engine/__init__.py
galigeopy/engine/engine.py
galigeopy/engine/osrm_engine.py
galigeopy/model/__init__.py
galigeopy/model/cluster_session.py
galigeopy/model/distancier_session.py
galigeopy/model/geolevel.py
galigeopy/model/geolevel_data_type.py
galigeopy/model/network.py
galigeopy/model/poi.py
galigeopy/model/zone.py
galigeopy/model/zone_geounit.py
galigeopy/model/zone_type.py
galigeopy/model/properties/__init__.py
galigeopy/model/properties/distancier_properties.py
galigeopy/model/properties/geolevel_properties.py
galigeopy/model/properties/geoleveldata_type_properties.py
galigeopy/model/properties/network_properties.py
galigeopy/model/properties/property.py
galigeopy/model/properties/zone_type_properties.py
galigeopy/org/__init__.py
galigeopy/org/org.py
galigeopy/utils/__init__.py
galigeopy/utils/spherical_calculus.py
galigeopy/utils/types.py
tests/model/__init__.py
tests/model/test_geolevel.py
tests/model/test_network.py
tests/model/test_poi.py
tests/model/test_zone.py
tests/model/test_zone_geounit.py
tests/model/test_zone_type.py
tests/org/__init__.py
tests/org/test_org.py
galigeopy-0.0.51.dist-info/METADATA
galigeopy-0.0.51.dist-info/WHEEL
galigeopy-0.0.51.dist-info/top_level.txt
galigeopy-0.0.51.dist-info/RECORD
