Metadata-Version: 2.4
Name: galigeopy
Version: 0.0.51
Summary: Galigeo Python SDK
Home-page: https://github.com/JPTGGO/galigeopy
Author: Jules Pierrat
Author-email: jpierrat@galigeo.com
License: Apache License 2.0
Project-URL: Source Code, https://github.com/JPTGGO/galigeopy
Classifier: Development Status :: 3 - Alpha
Classifier: Environment :: Console
Classifier: Environment :: Web Environment
Classifier: Intended Audience :: Developers
Classifier: Intended Audience :: Science/Research
Classifier: License :: OSI Approved :: Apache Software License
Classifier: Programming Language :: Python :: 3.10
Requires-Python: >=3.8
Dynamic: author
Dynamic: author-email
Dynamic: classifier
Dynamic: description
Dynamic: description-content-type
Dynamic: home-page
Dynamic: license
Dynamic: project-url
Dynamic: requires-python
Dynamic: summary
